MANIFEST.in
README.md
setup.cfg
setup.py
magapi/VERSION
magapi/__init__.py
magapi/author.py
magapi/constants.py
magapi/exceptions.py
magapi/logger.py
magapi/paper.py
magapi/study_field.py
magapi/utils.py
magapi_wrapper.egg-info/PKG-INFO
magapi_wrapper.egg-info/SOURCES.txt
magapi_wrapper.egg-info/dependency_links.txt
magapi_wrapper.egg-info/entry_points.txt
magapi_wrapper.egg-info/not-zip-safe
magapi_wrapper.egg-info/requires.txt
magapi_wrapper.egg-info/top_level.txt
tool/__init__.py
tool/wrapper.py