Metadata-Version: 2.1
Name: magapi-wrapper
Version: 1.3
Summary: Tool to download publications from Microsoft Academic Knowledge API
Home-page: https://github.com/bethgelab/magapi-wrapper
Author: Kantharaju Narayanappa
Author-email: kantharajucn@outlook.com
License: UNKNOWN
Keywords: Microsoft Academic graph,MAG,Knowledge API,Publications
Platform: UNKNOWN
Classifier: Development Status :: 4 - Beta
Classifier: Intended Audience :: Science/Research
Classifier: License :: OSI Approved :: Apache Software License
Classifier: Programming Language :: Python :: 3.7
Classifier: Topic :: Scientific/Engineering :: Information Analysis
Provides-Extra: testing
